[{"name": "100bot", "extras_name": "100bot", "version": "1.0.1", "pip_string": "100bot", "extras": [], "dependencies": [{"name": "requests", "extras_name": "requests", "version": "2.28.2", "pip_string": "requests", "extras": [], "dependencies": [{"name": "certifi", "extras_name": "certifi", "version": "2022.12.7", "pip_string": "certifi>=2017.4.17", "extras": []}, {"name": "charset-normalizer", "extras_name": "charset-normalizer", "version": "3.1.0", "pip_string": "charset-normalizer<4,>=2", "extras": []}, {"name": "idna", "extras_name": "idna", "version": "3.4", "pip_string": "idna<4,>=2.5", "extras": []}, {"name": "urllib3", "extras_name": "urllib3", "version": "1.26.15", "pip_string": "urllib3<1.27,>=1.21.1", "extras": []}]}, {"name": "slackclient", "extras_name": "slackclient", "version": "2.9.4", "pip_string": "slackclient", "extras": [], "dependencies": [{"name": "aiohttp", "extras_name": "aiohttp", "version": "3.8.4", "pip_string": "aiohttp<4.0.0,>3.5.2", "extras": [], "dependencies": [{"name": "aiosignal", "extras_name": "aiosignal", "version": "1.3.1", "pip_string": "aiosignal>=1.1.2", "extras": [], "dependencies": [{"name": "frozenlist", "extras_name": "frozenlist", "version": "1.3.3", "pip_string": "frozenlist>=1.1.0", "extras": []}]}, {"name": "async-timeout", "extras_name": "async-timeout", "version": "4.0.2", "pip_string": "async-timeout<5.0,>=4.0.0a3", "extras": []}, {"name": "attrs", "extras_name": "attrs", "version": "22.2.0", "pip_string": "attrs>=17.3.0", "extras": []}, {"name": "charset-normalizer", "extras_name": "charset-normalizer", "version": "3.1.0", "pip_string": "charset-normalizer<4.0,>=2.0", "extras": []}, {"name": "frozenlist", "extras_name": "frozenlist", "version": "1.3.3", "pip_string": "frozenlist>=1.1.1", "extras": []}, {"name": "multidict", "extras_name": "multidict", "version": "6.0.4", "pip_string": "multidict<7.0,>=4.5", "extras": []}, {"name": "yarl", "extras_name": "yarl", "version": "1.8.2", "pip_string": "yarl<2.0,>=1.0", "extras": [], "dependencies": [{"name": "idna", "extras_name": "idna", "version": "3.4", "pip_string": "idna>=2.0", "extras": []}, {"name": "multidict", "extras_name": "multidict", "version": "6.0.4", "pip_string": "multidict>=4.0", "extras": []}]}]}]}]}]
